ozcore/__init__.py
ozcore/_version.py
ozcore/core/__init__.py
ozcore/core/aggrid/__init__.py
ozcore/core/aggrid/aggrid.py
ozcore/core/data/__init__.py
ozcore/core/data/csv/__init__.py
ozcore/core/data/csv/base.py
ozcore/core/data/csv/process.py
ozcore/core/data/sqlite/__init__.py
ozcore/core/data/sqlite/orm.py
ozcore/core/data/sqlite/sqlite.py
ozcore/core/df/__init__.py
ozcore/core/df/dataframe.py
ozcore/core/df/dummy.py
ozcore/core/df/pareto_ranking.py
ozcore/core/path/__init__.py
ozcore/core/path/folders.py
ozcore/core/path/tmp_folders.py
ozcore/core/utils/__import_check.py
ozcore/core/utils/__init__.py
ozcore/core/utils/helper.py
ozcore/core/utils/html_markdown.py
ozcore/core/utils/jupyter.py
ozcore/core/utils/temporal.py
ozcore/core/utils/zipper.py
ozcore-2.1.1.dist-info/LICENSE
ozcore-2.1.1.dist-info/METADATA
ozcore-2.1.1.dist-info/WHEEL
ozcore-2.1.1.dist-info/RECORD
