Metadata-Version: 2.1
Name: ozcore
Version: 2.1.1
Summary: My core.
Home-page: https://ozcore.readthedocs.io/
License: GPL-3.0-or-later
Author: Ozgur Kalan
Author-email: ozgurkalan@gmail.com
Requires-Python: >=3.10,<4.0
Classifier: Development Status :: 5 - Production/Stable
Classifier: Intended Audience :: Developers
Classifier: License :: OSI Approved :: GNU General Public License v3 or later (GPLv3+)
Classifier: Programming Language :: Python :: 3
Classifier: Programming Language :: Python :: 3.10
Classifier: Programming Language :: Python :: 3.11
Classifier: Programming Language :: Python :: 3.9
Classifier: Topic :: Software Development :: Libraries :: Python Modules
Provides-Extra: all
Requires-Dist: alembic (>=1.11.2,<2.0.0)
Requires-Dist: dateparser (>=1.1.8,<2.0.0) ; extra == "all"
Requires-Dist: duckdb (>=0.8.1,<0.9.0) ; extra == "all"
Requires-Dist: dynaconf (>=3.1.12,<4.0.0) ; extra == "all"
Requires-Dist: faker (>=19.3.0,<20.0.0) ; extra == "all"
Requires-Dist: html2text (>=2020.1.16,<2021.0.0) ; extra == "all"
Requires-Dist: html5lib (>=1.1,<2.0) ; extra == "all"
Requires-Dist: ibis-framework (>=6.1.0,<7.0.0) ; extra == "all"
Requires-Dist: ipyaggrid (>=0.4.1,<0.5.0) ; extra == "all"
Requires-Dist: ipykernel (>=6.22.0,<7.0.0) ; extra == "all"
Requires-Dist: ipython (>=8.14.0,<9.0.0) ; extra == "all"
Requires-Dist: ipywidgets (>=8.0.6,<9.0.0) ; extra == "all"
Requires-Dist: jupyter (>=1.0.0,<2.0.0)
Requires-Dist: jupyter-contrib-nbextensions (>=0.7.0,<0.8.0) ; extra == "all"
Requires-Dist: jupyterlab (>=4.0.4,<5.0.0)
Requires-Dist: lxml (>=4.9.2,<5.0.0) ; extra == "all"
Requires-Dist: markdown2 (>=2.4.10,<3.0.0) ; extra == "all"
Requires-Dist: matplotlib (>=3.7.1,<4.0.0) ; extra == "all"
Requires-Dist: nbformat (>=5.8.0,<6.0.0) ; extra == "all"
Requires-Dist: notebook (>=7.0.2,<8.0.0) ; extra == "all"
Requires-Dist: numpy (>=1.25.2,<2.0.0)
Requires-Dist: pandas (>=2.0.3,<3.0.0)
Requires-Dist: pydantic (>=1.10.7,<2.0.0) ; extra == "all"
Requires-Dist: requests (>=2.28.2,<3.0.0) ; extra == "all"
Requires-Dist: seaborn (>=0.12.2,<0.13.0) ; extra == "all"
Requires-Dist: sqlalchemy (>=2.0.19,<3.0.0)
Requires-Dist: tqdm (>=4.65.0,<5.0.0) ; extra == "all"
Requires-Dist: typeguard (>=4.1.0,<5.0.0)
Requires-Dist: typer (>=0.7.0,<0.8.0)
Project-URL: Repository, https://github.com/ozgurkalan/OzCore
